usaspending/__init__.py
usaspending/cli/__init__.py
usaspending/cli/download_award.py
usaspending/client.py
usaspending/config.py
usaspending/download/__init__.py
usaspending/download/job.py
usaspending/download/manager.py
usaspending/exceptions.py
usaspending/logging_config.py
usaspending/models/__init__.py
usaspending/models/agency.py
usaspending/models/award.py
usaspending/models/award_factory.py
usaspending/models/award_types.py
usaspending/models/base_model.py
usaspending/models/contract.py
usaspending/models/district_spending.py
usaspending/models/download.py
usaspending/models/funding.py
usaspending/models/grant.py
usaspending/models/idv.py
usaspending/models/lazy_record.py
usaspending/models/loan.py
usaspending/models/location.py
usaspending/models/period_of_performance.py
usaspending/models/recipient.py
usaspending/models/recipient_business_categories.py
usaspending/models/recipient_spending.py
usaspending/models/spending.py
usaspending/models/state_spending.py
usaspending/models/subaward.py
usaspending/models/subtier_agency.py
usaspending/models/transaction.py
usaspending/queries/__init__.py
usaspending/queries/agencies_search.py
usaspending/queries/agency_award_summary.py
usaspending/queries/agency_query.py
usaspending/queries/award_query.py
usaspending/queries/awarding_agencies_search.py
usaspending/queries/awards_search.py
usaspending/queries/filters.py
usaspending/queries/funding_agencies_search.py
usaspending/queries/funding_search.py
usaspending/queries/query_builder.py
usaspending/queries/recipient_query.py
usaspending/queries/recipients_search.py
usaspending/queries/single_resource_base.py
usaspending/queries/spending_search.py
usaspending/queries/sub_agency_query.py
usaspending/queries/subawards_search.py
usaspending/queries/transactions_search.py
usaspending/resources/__init__.py
usaspending/resources/agency_resource.py
usaspending/resources/award_resource.py
usaspending/resources/base_resource.py
usaspending/resources/download_resource.py
usaspending_orm-0.7.0.dist-info/METADATA
usaspending_orm-0.7.0.dist-info/WHEEL
usaspending_orm-0.7.0.dist-info/licenses/LICENSE
usaspending_orm-0.7.0.dist-info/RECORD
