Metadata-Version: 2.4
Name: usaspending-orm
Version: 0.7.0
Summary: A Python ORM wrapper for the USAspending.gov API with intuitive queries, automatic pagination, and smart caching
License-Expression: MIT
License-File: LICENSE
Keywords: usaspending,federal-spending,government-data,api-wrapper,orm,contracts,grants
Author: Casey Dreier
Author-email: casey.dreier@planetary.org
Requires-Python: >=3.9
Classifier: Development Status :: 4 - Beta
Classifier: Intended Audience :: Developers
Classifier: Programming Language :: Python :: 3
Classifier: Programming Language :: Python :: 3.9
Classifier: Programming Language :: Python :: 3.10
Classifier: Programming Language :: Python :: 3.11
Classifier: Programming Language :: Python :: 3.12
Classifier: Topic :: Software Development :: Libraries :: Python Modules
Requires-Dist: cachier (>=4.1.0,<5.0.0)
Requires-Dist: pyyaml (>=6.0.2,<7.0.0)
Requires-Dist: requests (>=2.32.4,<3.0.0)
Requires-Dist: titlecase (>=2.4.1,<3.0.0)
Project-URL: Documentation, https://github.com/planetary-society/usaspending-orm/blob/main/README.md
Project-URL: Homepage, https://github.com/planetary-society/usaspending-orm
Project-URL: Issues, https://github.com/planetary-society/usaspending-orm/issues
Project-URL: Repository, https://github.com/planetary-society/usaspending-orm
